{
  "id": "511890100000",
  "language": "en",
  "name": "Grether's Pastillen Blackcurrant - schwarze Johanisbeere",
  "names": {
    "short_name": "Grether's Pastillen Blackcurrant - schwarze Johanisbeere"
  },
  "slug": "grethers-pastillen-blackcurrant-schwarze-johanisbeere",
  "slugs": {
    "de": "grethers-pastillen-blackcurrant-schwarze-johanisbeere",
    "fr": "grethers-pastillen-blackcurrant-cassis",
    "it": "grethers-pastillen-blackcurrant-ribes-nero",
    "en": "grethers-pastillen-blackcurrant-schwarze-johanisbeere"
  },
  "type": "00",
  "boss_number": "090322230535",
  "description": {
    "text": "Grether&rsquo;s Pastilles Blackcurrant – unser traditionsreiches Original mit dem naturreinen Saft der Schwarzen Johannisbeere. \n\n Die unvergleichlich fruchtig-milde Essenz gibt unseren wohltuenden Pastillen den unverkennbaren Geschmack und das pr&auml;gnante, tiefdunkle Aussehen. Grether&rsquo;s Pastilles Blackcurrant gibt es mit Zucker und in zuckerfrei mit den S&uuml;ssungsmitteln Maltitsirup und Acesulfam-K. \n Verwenden Sie Grether&rsquo;s Pastilles Blackcurrant schon bei den ersten Anzeichen von Beschwerden und geniessen Sie den intensiven Fruchtgeschmack der Schwarzen Johannisbeere mit allen Sinnen.",
    "source": "PEX"
  },
  "data_source": "SAP-X11",
  "status": {
    "id": "available",
    "seasonal": false,
    "pim_status": "03"
  },
  "tags": [
    "source-pex",
    "near-non-food",
    "migipedia",
    "migrolino-data",
    "view-browse-partial",
    "view-browse-all-retailers-partial"
  ],
  "is_variant": false,
  "gtins": [
    "7614700002061"
  ],
  "retailer": {
    "id": "supermarkt",
    "name": "Supermarket"
  },
  "retailer_flags": {
    "bikeworld": {
      "orderable": false,
      "reservable": false,
      "stock_request": false,
      "visible": false,
      "exclude_cross_channel": []
    },
    "doitgarden": {
      "orderable": false,
      "reservable": false,
      "stock_request": false,
      "visible": false,
      "exclude_cross_channel": []
    },
    "interio": {
      "orderable": false,
      "reservable": false,
      "stock_request": false,
      "visible": false,
      "exclude_cross_channel": []
    },
    "melectronics": {
      "orderable": false,
      "reservable": false,
      "stock_request": false,
      "visible": false,
      "exclude_cross_channel": []
    },
    "micasa": {
      "orderable": false,
      "reservable": false,
      "stock_request": false,
      "visible": false,
      "exclude_cross_channel": []
    },
    "migros_ch": {
      "orderable": false,
      "reservable": false,
      "stock_request": false,
      "visible": true,
      "exclude_cross_channel": []
    },
    "sportxx": {
      "orderable": false,
      "reservable": false,
      "stock_request": false,
      "visible": false,
      "exclude_cross_channel": []
    }
  },
  "brand": {
    "id": "J49",
    "name": "Grether's",
    "slug": "grethers"
  },
  "categories": [
    {
      "code": "BeSS_011201",
      "name": "Hausapotheke",
      "slug": "supermarkt/gesundheit/hausapotheke",
      "visible": true,
      "parent_code": "BeSS_0112",
      "level": 3
    },
    {
      "code": "BeSS_0112",
      "name": "Gesundheit",
      "slug": "supermarkt/gesundheit",
      "visible": true,
      "parent_code": "BeSS_01",
      "image": {
        "original": "https://image.migros.ch/original/832762761a56d78835c380db87e2aa4ecd7a4eed/gesundheit.jpg",
        "stack": "https://image.migros.ch/{stack}/832762761a56d78835c380db87e2aa4ecd7a4eed/gesundheit.jpg"
      },
      "level": 2
    },
    {
      "code": "BeSS_01",
      "name": "Supermarkt",
      "slug": "supermarkt",
      "visible": true,
      "parent_code": "root",
      "level": 1
    }
  ],
  "online_relevant": [
    {
      "code": "MGB",
      "name": "Migros Genossenschafts-Bund"
    }
  ],
  "galaxus_relevant": false,
  "links": {
    "migros_ch": {
      "url": "https://www.migros.ch/en/product/511890100000?context=instore",
      "name": "In-store assortment",
      "canonical": "https://www.migros.ch/en/product/511890100000?context=instore",
      "type": "info",
      "purchasable": false
    },
    "migros_online": {
      "url": "https://www.migros.ch/en/product/511890100000?context=online",
      "mo_product_id": "10499577",
      "name": "Online-shop assortment",
      "canonical": "https://www.migros.ch/en/product/511890100000?context=instore",
      "type": "shop",
      "purchasable": true,
      "one_catalog_id": 100058862
    },
    "migipedia": {
      "url": "https://migipedia.migros.ch/de/products/511890100000",
      "name": "Migipedia",
      "canonical": "https://www.migros.ch/en/product/511890100000?context=instore",
      "type": "info",
      "purchasable": false
    }
  },
  "receipt_text": "Grether's Past. BC 60g",
  "package": {
    "content": 60,
    "content_unit_code": "g",
    "content_unit": "Gramm",
    "net_weight": 0.093,
    "net_weight_unit_code": "kg",
    "net_weight_unit": "Kilogramm",
    "brutto_weight": 0.093,
    "brutto_weight_unit_code": "kg",
    "brutto_volume": 105.4,
    "brutto_volume_unit_code": "ccm",
    "height": 6.2,
    "length": 10,
    "width": 1.7,
    "unit_dimension": "cm",
    "price_comparison_content": 10,
    "size": "60g"
  },
  "package_information": {
    "tu": {
      "gtins": [
        "7614700801077"
      ],
      "brutto_weight": 1.2,
      "brutto_weight_unit_code": "kg",
      "brutto_volume": 1.82,
      "brutto_volume_unit_code": "cdm",
      "height": 7,
      "length": 20,
      "width": 13,
      "dimension_unit_code": "cm",
      "number_of_base_units": 12
    },
    "cu": {
      "gtins": [
        "7614700002061"
      ],
      "brutto_weight": 0.093,
      "brutto_weight_unit_code": "kg",
      "brutto_volume": 105.4,
      "brutto_volume_unit_code": "ccm",
      "height": 6.2,
      "length": 10,
      "width": 1.7,
      "dimension_unit_code": "cm",
      "number_of_base_units": 1
    },
    "lu": {
      "number_of_base_units": 5304
    },
    "lge": {
      "number_of_base_units": 408
    },
    "kar": {
      "number_of_base_units": 1
    }
  },
  "vat": {
    "id": 2,
    "percentage": 2.5
  },
  "price": {
    "valid_from": "2018-01-29T00:00:00+0100",
    "valid_to": "9999-12-31T23:59:59+0100",
    "currency": "CHF",
    "source": "PriceRepository",
    "item": {
      "price": 5.9,
      "quantity": 1,
      "unit": "CU",
      "varying_quantity": false,
      "display_quantity": "60g"
    },
    "base": {
      "price": 0.98,
      "quantity": 10,
      "unit": "g"
    }
  },
  "features": [
    {
      "label_code": "miso_geeignet_fuer",
      "label": "Suitable for",
      "values": [
        {
          "value_code": "MISO_geeignet_fuer_erkaeltung",
          "value": "Erkältung"
        }
      ],
      "category_code": "MISO_CLA_Hausapotheke_Gesundheit_Alle",
      "top_fact": false,
      "facet_flag": false,
      "facet_pictogram_flag": false
    }
  ],
  "image": {
    "original": "https://image.migros.ch/original/67456e326232314eeb1f4d26e766b54a2d2642f8/grethers-pastillen-blackcurrant-schwarze-johanisbeere.jpg",
    "stack": "https://image.migros.ch/{stack}/67456e326232314eeb1f4d26e766b54a2d2642f8/grethers-pastillen-blackcurrant-schwarze-johanisbeere.jpg"
  },
  "image_transparent": {
    "original": "https://image.migros.ch/original/13adbdee4d9d971221b0b178b238c47db8bb5380/grethers-pastillen-blackcurrant-schwarze-johanisbeere.png",
    "stack": "https://image.migros.ch/{stack}/13adbdee4d9d971221b0b178b238c47db8bb5380/grethers-pastillen-blackcurrant-schwarze-johanisbeere.png"
  },
  "internal_features": [
    {
      "label_code": "miso_amigos_anzeige",
      "label": "Display aMigos!",
      "values": [
        {
          "value_code": "MISO_aMigos_anzeige_ja",
          "value": "ja"
        }
      ],
      "category_code": "MISO_CLA_aMigos_Alle",
      "top_fact": false,
      "facet_flag": false,
      "facet_pictogram_flag": false
    },
    {
      "label_code": "miso_amigos_sortierung",
      "label": "aMigos sorting",
      "values": [
        {
          "value": "380"
        }
      ],
      "category_code": "MISO_CLA_aMigos_Alle",
      "top_fact": false,
      "facet_flag": false,
      "facet_pictogram_flag": false
    },
    {
      "label_code": "miso_amigos_volumen",
      "label": "aMigos! volume",
      "values": [
        {
          "value_code": "NUMERIC_0.1054",
          "value": "0.1054 l",
          "numeric_value": 0.1054
        }
      ],
      "category_code": "MISO_CLA_aMigos_Alle",
      "top_fact": false,
      "unit_code": "l",
      "unit": "Liter",
      "unit_symbol": "l",
      "facet_flag": false,
      "facet_pictogram_flag": false
    },
    {
      "label_code": "MAPI_GENERAL_POSITION_GROUP",
      "values": [
        {
          "value_code": "NORM",
          "value": "Standard item"
        }
      ],
      "category_code": "MAPI_GENERAL_POSITION_GROUP",
      "top_fact": false
    },
    {
      "label_code": "MAPI_ARTICLE_VARIETY",
      "values": [
        {
          "value": "ZHKS"
        }
      ],
      "category_code": "MAPI_ARTICLE_VARIETY",
      "top_fact": false
    },
    {
      "label_code": "MAPI_CUSTOMS_POSITION",
      "values": [
        {
          "value": "2106.9040"
        }
      ],
      "category_code": "MAPI_CUSTOMS_POSITION",
      "top_fact": false
    },
    {
      "label_code": "MAPI_RISK_CLASS",
      "values": [
        {
          "value_code": "1",
          "value": "1 (high)"
        }
      ],
      "category_code": "MAPI_RISK_CLASS",
      "top_fact": false
    },
    {
      "label_code": "MAPI_QUALITY_CHECK",
      "values": [
        {
          "value_code": "00",
          "value": "No Quality Control"
        }
      ],
      "category_code": "MAPI_QUALITY_CHECK",
      "top_fact": false
    },
    {
      "label_code": "MAPI_PRODUCT_KIND",
      "values": [
        {
          "value_code": "ZHKS",
          "value": "HKS Standardartikel"
        }
      ],
      "category_code": "MAPI_PRODUCT_KIND",
      "top_fact": false
    },
    {
      "label_code": "MAPI_ASSORTMENT_LIST_KIND",
      "values": [
        {
          "value_code": "H",
          "value": "HKS Standard"
        }
      ],
      "category_code": "MAPI_ASSORTMENT_LIST_KIND",
      "top_fact": false
    },
    {
      "label_code": "MAPI_PRODUCT_GROUP",
      "values": [
        {
          "value_code": "50385",
          "value": "SELBSTMEDIKATION"
        }
      ],
      "category_code": "MAPI_PRODUCT_GROUP",
      "top_fact": false
    },
    {
      "label_code": "MAPI_CUMULUS_POINTS_CODE",
      "values": [
        {
          "value_code": "NUMERIC_2",
          "value": "2",
          "numeric_value": 2
        }
      ],
      "category_code": "MAPI_CUMULUS_POINTS_CODE",
      "top_fact": false
    },
    {
      "label_code": "MAPI_PROMOTIONS_CODE",
      "values": [
        {
          "value_code": "NUMERIC_1",
          "value": "1",
          "numeric_value": 1
        }
      ],
      "category_code": "MAPI_PROMOTIONS_CODE",
      "top_fact": false
    },
    {
      "label_code": "MAPI_LIFECYCLE",
      "values": [
        {
          "value_code": "D",
          "value": "Detailhandelsartikel"
        }
      ],
      "category_code": "MAPI_LIFECYCLE",
      "top_fact": false
    },
    {
      "label_code": "MAPI_BRANCH_ORDER_BLOCK",
      "values": [
        {
          "value_code": "BOOLEAN_FALSE",
          "value": "No",
          "boolean_value": false
        }
      ],
      "category_code": "MAPI_BRANCH_ORDER_BLOCK",
      "top_fact": false
    },
    {
      "label_code": "MAPI_EXPORTABLE",
      "values": [
        {
          "value_code": "BOOLEAN_TRUE",
          "value": "Yes",
          "boolean_value": true
        }
      ],
      "category_code": "MAPI_EXPORTABLE",
      "top_fact": false
    }
  ],
  "regional_availability": {
    "gmaa": {
      "probability": 100
    },
    "gmbs": {
      "probability": 98
    },
    "gmge": {
      "probability": 89
    },
    "gmlu": {
      "probability": 97
    },
    "gmnf": {
      "probability": 100
    },
    "gmos": {
      "probability": 98
    },
    "gmti": {
      "probability": 100
    },
    "gmvd": {
      "probability": 96
    },
    "gmvs": {
      "probability": 96
    },
    "gmzh": {
      "probability": 95
    }
  },
  "ratings": {
    "count_all": 16,
    "average_all": 4.1875
  },
  "reindex_date": "9999-12-31T00:00:00+0100",
  "updated_at": "2023-08-17T12:00:22+0200",
  "sap_created_at": "2013-02-26T00:00:00+0100",
  "base_unit": "CU",
  "views": [
    "all",
    "browse",
    "browseallretailers"
  ]
}
