{
  "id": "514629000000",
  "language": "en",
  "name": "I am Daily Care Shampoo",
  "names": {
    "short_name": "I am Daily Care Shampoo"
  },
  "slug": "i-am-daily-care-shampoo",
  "slugs": {
    "de": "i-am-daily-care-shampoo",
    "fr": "i-am-daily-care-shampooing",
    "it": "i-am-daily-care-shampoo",
    "en": "i-am-daily-care-shampoo"
  },
  "type": "00",
  "boss_number": "090121671506",
  "description": {
    "text": "Schonende Reinigung, t&auml;gliche Pflege. \nDas Daily Care Shampoo f&uuml;r eine sanfte Reinigung ohne Silikone, erh&auml;lt die nat&uuml;rliche Feuchtigkeitsbalance des Haares,\nhilft Stylingr&uuml;ckst&auml;nde auf dem Haar gr&uuml;ndlich zu entfernen.",
    "source": "PEX"
  },
  "data_source": "SAP-X11",
  "status": {
    "id": "available",
    "seasonal": false,
    "pim_status": "03"
  },
  "tags": [
    "source-pex",
    "near-non-food",
    "migipedia",
    "view-browse-partial",
    "view-browse-all-retailers-partial"
  ],
  "is_variant": false,
  "gtins": [
    "7613269344384"
  ],
  "retailer": {
    "id": "supermarkt",
    "name": "Supermarket"
  },
  "retailer_flags": {
    "bikeworld": {
      "orderable": false,
      "reservable": false,
      "stock_request": false,
      "visible": false,
      "exclude_cross_channel": []
    },
    "doitgarden": {
      "orderable": false,
      "reservable": false,
      "stock_request": false,
      "visible": false,
      "exclude_cross_channel": []
    },
    "interio": {
      "orderable": false,
      "reservable": false,
      "stock_request": false,
      "visible": false,
      "exclude_cross_channel": []
    },
    "melectronics": {
      "orderable": false,
      "reservable": false,
      "stock_request": false,
      "visible": false,
      "exclude_cross_channel": []
    },
    "micasa": {
      "orderable": false,
      "reservable": false,
      "stock_request": false,
      "visible": false,
      "exclude_cross_channel": []
    },
    "migros_ch": {
      "orderable": false,
      "reservable": false,
      "stock_request": false,
      "visible": true,
      "exclude_cross_channel": []
    },
    "sportxx": {
      "orderable": false,
      "reservable": false,
      "stock_request": false,
      "visible": false,
      "exclude_cross_channel": []
    }
  },
  "brand": {
    "id": "651",
    "name": "I am",
    "slug": "i-am",
    "links": {
      "homepage": {
        "url": "https://produkte.migros.ch/marken/i-am",
        "name": "Homepage",
        "type": "info",
        "purchasable": false
      }
    },
    "image": {
      "original": "https://image.migros.ch/original/9fb80916576b8c289ac8cec1b8f9990b656d17ef/i-am.jpg",
      "stack": "https://image.migros.ch/{stack}/9fb80916576b8c289ac8cec1b8f9990b656d17ef/i-am.jpg"
    }
  },
  "categories": [
    {
      "code": "BeSS_01110101",
      "name": "Haarpflege",
      "slug": "supermarkt/beauty/haare/haarpflege",
      "visible": true,
      "parent_code": "BeSS_011101",
      "level": 4
    },
    {
      "code": "BeSS_011101",
      "name": "Haare",
      "slug": "supermarkt/beauty/haare",
      "visible": true,
      "parent_code": "BeSS_0111",
      "level": 3
    },
    {
      "code": "BeSS_0111",
      "name": "Beauty",
      "slug": "supermarkt/beauty",
      "visible": true,
      "parent_code": "BeSS_01",
      "image": {
        "original": "https://image.migros.ch/original/293925170bd129344f9259c67a15e903f881bef8/beauty.jpg",
        "stack": "https://image.migros.ch/{stack}/293925170bd129344f9259c67a15e903f881bef8/beauty.jpg"
      },
      "level": 2
    },
    {
      "code": "BeSS_01",
      "name": "Supermarkt",
      "slug": "supermarkt",
      "visible": true,
      "parent_code": "root",
      "level": 1
    }
  ],
  "online_relevant": [
    {
      "code": "MGB",
      "name": "Migros Genossenschafts-Bund"
    },
    {
      "code": "MO",
      "name": "Migros Online"
    }
  ],
  "galaxus_relevant": false,
  "links": {
    "migros_ch": {
      "url": "https://www.migros.ch/en/product/514629000000?context=instore",
      "name": "In-store assortment",
      "canonical": "https://www.migros.ch/en/product/514629000000?context=instore",
      "type": "info",
      "purchasable": false
    },
    "migros_online": {
      "url": "https://www.migros.ch/en/product/514629000000?context=online",
      "mo_product_id": "4423560",
      "name": "Online-shop assortment",
      "canonical": "https://www.migros.ch/en/product/514629000000?context=instore",
      "type": "shop",
      "purchasable": true,
      "one_catalog_id": 100044788
    },
    "migipedia": {
      "url": "https://migipedia.migros.ch/de/products/514629000000",
      "name": "Migipedia",
      "canonical": "https://www.migros.ch/en/product/514629000000?context=instore",
      "type": "info",
      "purchasable": false
    }
  },
  "m_check2": {
    "carbon_footprint": {
      "image": {
        "original": "https://image.migros.ch/original/6137c42cbff331738ddeafb4f91efb06075417b3.svg",
        "stack": "https://image.migros.ch/{stack}/6137c42cbff331738ddeafb4f91efb06075417b3.svg"
      },
      "ground_and_sea_cargo": {
        "kg_co2": 7.98,
        "kg_co2_range": "4.8 - 9.9 kg CO₂eq / kg",
        "co2_in_car_km": 44,
        "rating": 2,
        "production_in_percent": 97,
        "packaging_in_percent": 2,
        "transport_in_percent": 1
      }
    }
  },
  "receipt_text": "I am Classic Shampoo",
  "package": {
    "content": 250,
    "content_unit_code": "ml",
    "content_unit": "Mililiter",
    "net_weight": 0.257,
    "net_weight_unit_code": "kg",
    "net_weight_unit": "Kilogramm",
    "brutto_weight": 0.299,
    "brutto_weight_unit_code": "kg",
    "brutto_volume": 0.97,
    "brutto_volume_unit_code": "cdm",
    "height": 17.3,
    "length": 4,
    "width": 6.8,
    "unit_dimension": "cm",
    "price_comparison_content": 100,
    "size": "250ml"
  },
  "package_information": {
    "tu": {
      "gtins": [
        "7613269344391",
        "7630041418248"
      ],
      "brutto_weight": 2.7,
      "brutto_weight_unit_code": "kg",
      "brutto_volume": 5.7,
      "brutto_volume_unit_code": "cdm",
      "height": 19,
      "length": 20,
      "width": 15,
      "dimension_unit_code": "cm",
      "number_of_base_units": 9
    },
    "cu": {
      "gtins": [
        "7613269344384"
      ],
      "brutto_weight": 0.299,
      "brutto_weight_unit_code": "kg",
      "brutto_volume": 0.97,
      "brutto_volume_unit_code": "cdm",
      "height": 17.3,
      "length": 4,
      "width": 6.8,
      "dimension_unit_code": "cm",
      "number_of_base_units": 1
    },
    "lu": {
      "height": 166.5,
      "dimension_unit_code": "cm",
      "number_of_base_units": 2304
    },
    "lge": {
      "number_of_base_units": 1
    },
    "kar": {
      "number_of_base_units": 1
    }
  },
  "vat": {
    "id": 1,
    "percentage": 7.7
  },
  "price": {
    "valid_from": "2023-04-12T00:00:00+0200",
    "valid_to": "9999-12-31T23:59:59+0100",
    "currency": "CHF",
    "source": "PriceRepository",
    "item": {
      "price": 2.3,
      "quantity": 1,
      "unit": "CU",
      "varying_quantity": false,
      "display_quantity": "250ml"
    },
    "base": {
      "price": 0.92,
      "quantity": 100,
      "unit": "ML"
    }
  },
  "features": [
    {
      "label_code": "miso_produkttyp",
      "label": "Product type",
      "values": [
        {
          "value_code": "MISO_produkttyp_shampoo",
          "value": "Shampoo"
        }
      ],
      "category_code": "MISO_CLA_Haarpflege_Haare_Beauty_Alle",
      "top_fact": false,
      "facet_flag": false,
      "facet_pictogram_flag": false
    },
    {
      "label_code": "miso_geeignet_fuer",
      "label": "Suitable for",
      "values": [
        {
          "value_code": "MISO_geeignet_fuer_normaleshaar",
          "value": "Normales Haar"
        }
      ],
      "category_code": "MISO_CLA_Haarpflege_Haare_Beauty_Alle",
      "top_fact": false,
      "facet_flag": false,
      "facet_pictogram_flag": false
    },
    {
      "label_code": "miso_beduerfnis_nutzen",
      "label": "Requirements/uses",
      "values": [
        {
          "value_code": "MISO_beduerfnis_nutzen_feuchtigkeit",
          "value": "Feuchtigkeit"
        }
      ],
      "category_code": "MISO_CLA_Haarpflege_Haare_Beauty_Alle",
      "top_fact": false,
      "facet_flag": false,
      "facet_pictogram_flag": false
    }
  ],
  "image": {
    "original": "https://image.migros.ch/original/c48a1b8f2b9450b0d73e4f53b102de6e719e9bfa/i-am-daily-care-shampoo.jpg",
    "stack": "https://image.migros.ch/{stack}/c48a1b8f2b9450b0d73e4f53b102de6e719e9bfa/i-am-daily-care-shampoo.jpg"
  },
  "image_transparent": {
    "original": "https://image.migros.ch/original/34f5e511cb7424dd62b48b017f5fc5b6f64f6fb4/i-am-daily-care-shampoo.png",
    "stack": "https://image.migros.ch/{stack}/34f5e511cb7424dd62b48b017f5fc5b6f64f6fb4/i-am-daily-care-shampoo.png"
  },
  "internal_features": [
    {
      "label_code": "miso_amigos_anzeige",
      "label": "Display aMigos!",
      "values": [
        {
          "value_code": "MISO_aMigos_anzeige_ja",
          "value": "ja"
        }
      ],
      "category_code": "MISO_CLA_aMigos_Alle",
      "top_fact": false,
      "facet_flag": false,
      "facet_pictogram_flag": false
    },
    {
      "label_code": "miso_amigos_sortierung",
      "label": "aMigos sorting",
      "values": [
        {
          "value": "140"
        }
      ],
      "category_code": "MISO_CLA_aMigos_Alle",
      "top_fact": false,
      "facet_flag": false,
      "facet_pictogram_flag": false
    },
    {
      "label_code": "MAPI_GENERAL_POSITION_GROUP",
      "values": [
        {
          "value_code": "NORM",
          "value": "Standard item"
        }
      ],
      "category_code": "MAPI_GENERAL_POSITION_GROUP",
      "top_fact": false
    },
    {
      "label_code": "MAPI_ARTICLE_VARIETY",
      "values": [
        {
          "value": "ZHKS"
        }
      ],
      "category_code": "MAPI_ARTICLE_VARIETY",
      "top_fact": false
    },
    {
      "label_code": "MAPI_CUSTOMS_POSITION",
      "values": [
        {
          "value": "33053000000"
        }
      ],
      "category_code": "MAPI_CUSTOMS_POSITION",
      "top_fact": false
    },
    {
      "label_code": "MAPI_RISK_CLASS",
      "values": [
        {
          "value_code": "2",
          "value": "2 (medium)"
        }
      ],
      "category_code": "MAPI_RISK_CLASS",
      "top_fact": false
    },
    {
      "label_code": "MAPI_QUALITY_CHECK",
      "values": [
        {
          "value_code": "00",
          "value": "No Quality Control"
        }
      ],
      "category_code": "MAPI_QUALITY_CHECK",
      "top_fact": false
    },
    {
      "label_code": "MAPI_PRODUCT_KIND",
      "values": [
        {
          "value_code": "ZHKS",
          "value": "HKS Standardartikel"
        }
      ],
      "category_code": "MAPI_PRODUCT_KIND",
      "top_fact": false
    },
    {
      "label_code": "MAPI_ASSORTMENT_LIST_KIND",
      "values": [
        {
          "value_code": "H",
          "value": "HKS Standard"
        }
      ],
      "category_code": "MAPI_ASSORTMENT_LIST_KIND",
      "top_fact": false
    },
    {
      "label_code": "MAPI_PRODUCT_GROUP",
      "values": [
        {
          "value_code": "50038",
          "value": "I AM HAIR"
        }
      ],
      "category_code": "MAPI_PRODUCT_GROUP",
      "top_fact": false
    },
    {
      "label_code": "MAPI_CUMULUS_POINTS_CODE",
      "values": [
        {
          "value_code": "NUMERIC_2",
          "value": "2",
          "numeric_value": 2
        }
      ],
      "category_code": "MAPI_CUMULUS_POINTS_CODE",
      "top_fact": false
    },
    {
      "label_code": "MAPI_PROMOTIONS_CODE",
      "values": [
        {
          "value_code": "NUMERIC_1",
          "value": "1",
          "numeric_value": 1
        }
      ],
      "category_code": "MAPI_PROMOTIONS_CODE",
      "top_fact": false
    },
    {
      "label_code": "MAPI_LIFECYCLE",
      "values": [
        {
          "value_code": "D",
          "value": "Detailhandelsartikel"
        }
      ],
      "category_code": "MAPI_LIFECYCLE",
      "top_fact": false
    },
    {
      "label_code": "MAPI_BRANCH_ORDER_BLOCK",
      "values": [
        {
          "value_code": "BOOLEAN_FALSE",
          "value": "No",
          "boolean_value": false
        }
      ],
      "category_code": "MAPI_BRANCH_ORDER_BLOCK",
      "top_fact": false
    },
    {
      "label_code": "MAPI_EXPORTABLE",
      "values": [
        {
          "value_code": "BOOLEAN_TRUE",
          "value": "Yes",
          "boolean_value": true
        }
      ],
      "category_code": "MAPI_EXPORTABLE",
      "top_fact": false
    }
  ],
  "regional_availability": {
    "gmaa": {
      "probability": 99
    },
    "gmbs": {
      "probability": 100
    },
    "gmge": {
      "probability": 89
    },
    "gmlu": {
      "probability": 98
    },
    "gmnf": {
      "probability": 100
    },
    "gmos": {
      "probability": 98
    },
    "gmti": {
      "probability": 100
    },
    "gmvd": {
      "probability": 96
    },
    "gmvs": {
      "probability": 100
    },
    "gmzh": {
      "probability": 93
    }
  },
  "ratings": {
    "count_all": 24,
    "average_all": 4.25
  },
  "reindex_date": "9999-12-31T00:00:00+0100",
  "updated_at": "2023-08-17T12:03:10+0200",
  "sap_created_at": "2013-05-29T00:00:00+0200",
  "base_unit": "CU",
  "views": [
    "all",
    "browse",
    "browseallretailers"
  ]
}
