{
  "id": "702208200000",
  "language": "en",
  "name": "NACHFUELLBEUTEL LUFTENTFEUCHTER UHU",
  "names": {
    "short_name": "NACHFUELLBEUTEL LUFTENTFEUCHTER UHU"
  },
  "slug": "nachfuellbeutel-luftentfeuchter-uhu",
  "slugs": {
    "de": "luftentfeucher-nachfuellbeutel",
    "fr": "sachet-de-recharge-pour-deshumidificateur",
    "it": "confezione-di-ricarica-per-deumidificatore",
    "en": "nachfuellbeutel-luftentfeuchter-uhu"
  },
  "type": "00",
  "boss_number": "150224473005",
  "description": {
    "text": "Nachf&uuml;llbeutel f&uuml;r UHU Luftentfeuchter Modell: 350591",
    "source": "PEX"
  },
  "data_source": "SAP-X12",
  "status": {
    "id": "available",
    "seasonal": false,
    "pim_status": "03",
    "distribution_center": [
      {
        "center_id": "1001",
        "center_name": "Migros Verteilzentrum Neuendorf",
        "status_code": "03",
        "status_description": "active"
      }
    ]
  },
  "tags": [
    "source-pex",
    "near-non-food",
    "migipedia",
    "view-browse-partial",
    "view-browse-all-retailers-partial"
  ],
  "is_variant": false,
  "gtins": [
    "4026700470857"
  ],
  "retailer": {
    "id": "supermarkt",
    "name": "Supermarket"
  },
  "retailer_flags": {
    "bikeworld": {
      "orderable": false,
      "reservable": true,
      "stock_request": true,
      "visible": false,
      "exclude_cross_channel": []
    },
    "doitgarden": {
      "orderable": false,
      "reservable": true,
      "stock_request": true,
      "visible": false,
      "exclude_cross_channel": []
    },
    "interio": {
      "orderable": false,
      "reservable": true,
      "stock_request": true,
      "visible": false,
      "exclude_cross_channel": []
    },
    "melectronics": {
      "orderable": false,
      "reservable": true,
      "stock_request": true,
      "visible": false,
      "exclude_cross_channel": []
    },
    "micasa": {
      "orderable": false,
      "reservable": true,
      "stock_request": true,
      "visible": false,
      "exclude_cross_channel": []
    },
    "migros_ch": {
      "orderable": false,
      "reservable": false,
      "stock_request": false,
      "visible": true,
      "exclude_cross_channel": []
    },
    "sportxx": {
      "orderable": false,
      "reservable": true,
      "stock_request": true,
      "visible": false,
      "exclude_cross_channel": []
    }
  },
  "brand": {
    "id": "N74",
    "name": "Uhu",
    "slug": "uhu"
  },
  "categories": [
    {
      "code": "BeSS_01040508",
      "name": "Sonstiges",
      "slug": "supermarkt/haushalt-reinigung/haushaltshelfer-haushaltszubehoer/sonstiges",
      "visible": true,
      "parent_code": "BeSS_010405",
      "level": 4
    },
    {
      "code": "BeSS_010405",
      "name": "Haushaltshelfer & Haushaltszubehör",
      "slug": "supermarkt/haushalt-reinigung/haushaltshelfer-haushaltszubehoer",
      "visible": true,
      "title": "Haushalt und Haushaltszubehör finden Sie in Ihrer Migros",
      "parent_code": "BeSS_0104",
      "image": {
        "original": "https://image.migros.ch/original/0e476671f83799a9ccb6bb5847d6d19c67e426f2/haushaltshelfer-haushaltszubehoer.jpg",
        "stack": "https://image.migros.ch/{stack}/0e476671f83799a9ccb6bb5847d6d19c67e426f2/haushaltshelfer-haushaltszubehoer.jpg"
      },
      "level": 3
    },
    {
      "code": "BeSS_0104",
      "name": "Haushalt & Reinigung",
      "slug": "supermarkt/haushalt-reinigung",
      "visible": true,
      "title": "Reinigung mit der Migros – Reiniger für Haushalt und Garten",
      "parent_code": "BeSS_01",
      "image": {
        "original": "https://image.migros.ch/original/e5da3225980543e0c7ddcc443069f331d94e8439/haushalt-reinigung.png",
        "stack": "https://image.migros.ch/{stack}/e5da3225980543e0c7ddcc443069f331d94e8439/haushalt-reinigung.png"
      },
      "level": 2
    },
    {
      "code": "BeSS_01",
      "name": "Supermarkt",
      "slug": "supermarkt",
      "visible": true,
      "parent_code": "root",
      "level": 1
    }
  ],
  "online_relevant": [
    {
      "code": "MGB",
      "name": "Migros Genossenschafts-Bund"
    }
  ],
  "links": {
    "migros_ch": {
      "url": "https://www.migros.ch/en/product/702208200000?context=instore",
      "name": "In-store assortment",
      "canonical": "https://www.migros.ch/en/product/702208200000?context=instore",
      "type": "info",
      "purchasable": false
    },
    "migipedia": {
      "url": "https://migipedia.migros.ch/de/products/702208200000",
      "name": "Migipedia",
      "canonical": "https://www.migros.ch/en/product/702208200000?context=instore",
      "type": "info",
      "purchasable": false
    }
  },
  "receipt_text": "Nachfüllbeutel Luftent",
  "package": {
    "content": 1,
    "content_unit_code": "st",
    "content_unit": "Stück",
    "net_weight": 1,
    "net_weight_unit_code": "kg",
    "net_weight_unit": "Kilogramm",
    "brutto_weight": 1.064,
    "brutto_weight_unit_code": "kg",
    "brutto_volume": 2.362,
    "brutto_volume_unit_code": "cdm",
    "height": 31.5,
    "length": 5,
    "width": 15,
    "unit_dimension": "cm",
    "price_comparison_content": 1,
    "size": "1 Stk."
  },
  "package_information": {
    "cu": {
      "gtins": [
        "4026700470857"
      ],
      "brutto_weight": 1.064,
      "brutto_weight_unit_code": "kg",
      "brutto_volume": 2.362,
      "brutto_volume_unit_code": "cdm",
      "height": 31.5,
      "length": 5,
      "width": 15,
      "dimension_unit_code": "cm",
      "number_of_base_units": 1
    },
    "tuv": {
      "brutto_weight": 6.56,
      "brutto_weight_unit_code": "kg",
      "brutto_volume": 19.845,
      "brutto_volume_unit_code": "cdm",
      "height": 21,
      "length": 35,
      "width": 27,
      "dimension_unit_code": "cm",
      "number_of_base_units": 6
    },
    "tue": {
      "brutto_weight": 1,
      "brutto_weight_unit_code": "kg",
      "brutto_volume": 22.22,
      "brutto_volume_unit_code": "cdm",
      "height": 5,
      "length": 32,
      "width": 15,
      "dimension_unit_code": "cm",
      "number_of_base_units": 6
    },
    "lu": {
      "number_of_base_units": 12
    }
  },
  "vat": {
    "id": 1,
    "percentage": 7.7
  },
  "price": {
    "valid_from": "2018-01-30T00:00:00+0100",
    "valid_to": "9999-12-31T23:59:59+0100",
    "currency": "CHF",
    "source": "PriceRepository",
    "item": {
      "price": 12.5,
      "quantity": 1,
      "unit": "CU",
      "varying_quantity": false,
      "display_quantity": "1 Stk."
    },
    "base": {
      "price": 12.5,
      "quantity": 1,
      "unit": "st"
    }
  },
  "features": [
    {
      "label_code": "miso_anzahl",
      "label": "Number",
      "values": [
        {
          "value_code": "NUMERIC_1",
          "value": "1 Stk.",
          "numeric_value": 1
        }
      ],
      "category_code": "MISO_CLA_Haushaltshelfer_Verbrauch_Haushalt_Alle",
      "top_fact": false,
      "unit_code": "Stk.",
      "unit": "Stück",
      "unit_symbol": "Stk.",
      "facet_flag": false,
      "facet_pictogram_flag": false
    },
    {
      "label_code": "miso_masse_groesse",
      "label": "Dimensions/size",
      "values": [
        {
          "value": "15 x 31.5 x 5 cm"
        }
      ],
      "category_code": "MISO_CLA_Haushaltshelfer_Verbrauch_Haushalt_Alle",
      "top_fact": false,
      "facet_flag": false,
      "facet_pictogram_flag": false
    },
    {
      "label_code": "miso_material",
      "label": "Material",
      "values": [
        {
          "value_code": "MISO_material_calciumchlorid",
          "value": "Calciumchlorid"
        }
      ],
      "category_code": "MISO_CLA_Haushaltshelfer_Verbrauch_Haushalt_Alle",
      "top_fact": false,
      "facet_flag": false,
      "facet_pictogram_flag": false
    },
    {
      "label_code": "miso_farbe",
      "label": "Color",
      "values": [
        {
          "value_code": "MISO_farbe_weiss",
          "value": "weiss"
        }
      ],
      "category_code": "MISO_CLA_Haushaltshelfer_Verbrauch_Haushalt_Alle",
      "top_fact": false,
      "facet_flag": false,
      "facet_pictogram_flag": false
    },
    {
      "label_code": "miso_hinweis",
      "label": "Note",
      "values": [
        {
          "value": "Enthält Calciumchlorid. Reizt die Augen. Darf nicht in die Hände von Kindern gelangen. Staub nicht einatmen. Berührung mit der Haut vermeiden. Bei Verschlucken sofort ärztlichen Rat einholen und Verpackung oder Etikett vorzeigen. Bei Berührung mit den Augen sofort mit Wasser ausspülen und Arzt konsultieren. Bei Berührung mit der Haut sofort mit viel Wasser abwaschen."
        }
      ],
      "category_code": "MISO_CLA_Haushaltshelfer_Verbrauch_Haushalt_Alle",
      "top_fact": false,
      "facet_flag": false,
      "facet_pictogram_flag": false
    },
    {
      "label_code": "CHEMICALS_WARNING",
      "label": "Warning",
      "values": [
        {
          "value": "Always read label and product information before use."
        }
      ],
      "category_code": "CHEMICALS_WARNING",
      "top_fact": false
    }
  ],
  "image": {
    "original": "https://image.migros.ch/original/36c75bbcd5b14d574bb2b99f690dccbfe9c80315/nachfuellbeutel-luftentfeuchter-uhu.jpg",
    "stack": "https://image.migros.ch/{stack}/36c75bbcd5b14d574bb2b99f690dccbfe9c80315/nachfuellbeutel-luftentfeuchter-uhu.jpg"
  },
  "image_transparent": {
    "original": "https://image.migros.ch/original/cceee658107e6d9ee834e620e4930e6fd96bb63d/nachfuellbeutel-luftentfeuchter-uhu.png",
    "stack": "https://image.migros.ch/{stack}/cceee658107e6d9ee834e620e4930e6fd96bb63d/nachfuellbeutel-luftentfeuchter-uhu.png"
  },
  "internal_features": [
    {
      "label_code": "MAPI_DEFAULT_LOGISTIC_TYPE",
      "values": [
        {
          "value_code": "55",
          "value": "Versandart Paket"
        }
      ],
      "category_code": "MAPI_DEFAULT_LOGISTIC_TYPE",
      "top_fact": false
    },
    {
      "label_code": "MAPI_LOGISTIC_CLASS",
      "values": [
        {
          "value_code": "7",
          "value": "VMI"
        }
      ],
      "category_code": "MAPI_LOGISTIC_CLASS",
      "top_fact": false
    },
    {
      "label_code": "MAPI_GENERAL_POSITION_GROUP",
      "values": [
        {
          "value_code": "NORM",
          "value": "Standard item"
        }
      ],
      "category_code": "MAPI_GENERAL_POSITION_GROUP",
      "top_fact": false
    },
    {
      "label_code": "MAPI_ARTICLE_VARIETY",
      "values": [
        {
          "value": "HART"
        }
      ],
      "category_code": "MAPI_ARTICLE_VARIETY",
      "top_fact": false
    },
    {
      "label_code": "MAPI_CUSTOMS_POSITION",
      "values": [
        {
          "value": "00028272000"
        }
      ],
      "category_code": "MAPI_CUSTOMS_POSITION",
      "top_fact": false
    },
    {
      "label_code": "MAPI_PRESENTATION",
      "values": [
        {
          "value_code": "L",
          "value": "liegend"
        }
      ],
      "category_code": "MAPI_PRESENTATION",
      "top_fact": false
    },
    {
      "label_code": "MAPI_RISK_CLASS",
      "values": [
        {
          "value_code": "1",
          "value": "1 (high)"
        }
      ],
      "category_code": "MAPI_RISK_CLASS",
      "top_fact": false
    },
    {
      "label_code": "MAPI_QUALITY_CHECK",
      "values": [
        {
          "value_code": "00",
          "value": "No Quality Control"
        }
      ],
      "category_code": "MAPI_QUALITY_CHECK",
      "top_fact": false
    },
    {
      "label_code": "MAPI_KUBE_TUKA",
      "values": [
        {
          "value_code": "BLANK",
          "value": "KUBE und TUKA nicht zugelassen"
        }
      ],
      "category_code": "MAPI_KUBE_TUKA",
      "top_fact": false
    },
    {
      "label_code": "MAPI_PRODUCT_KIND",
      "values": [
        {
          "value_code": "HART",
          "value": "Hartwaren Handelsware"
        }
      ],
      "category_code": "MAPI_PRODUCT_KIND",
      "top_fact": false
    },
    {
      "label_code": "MAPI_ASSORTMENT_LIST_KIND",
      "values": [
        {
          "value_code": "H",
          "value": "Hartwaren"
        }
      ],
      "category_code": "MAPI_ASSORTMENT_LIST_KIND",
      "top_fact": false
    },
    {
      "label_code": "MAPI_PRODUCT_GROUP",
      "values": [
        {
          "value_code": "60983",
          "value": "LUFTBE- UND ENTFEUCHTER"
        }
      ],
      "category_code": "MAPI_PRODUCT_GROUP",
      "top_fact": false
    },
    {
      "label_code": "MAPI_CUMULUS_POINTS_CODE",
      "values": [
        {
          "value_code": "NUMERIC_2",
          "value": "2",
          "numeric_value": 2
        }
      ],
      "category_code": "MAPI_CUMULUS_POINTS_CODE",
      "top_fact": false
    },
    {
      "label_code": "MAPI_PROMOTIONS_CODE",
      "values": [
        {
          "value_code": "NUMERIC_1",
          "value": "1",
          "numeric_value": 1
        }
      ],
      "category_code": "MAPI_PROMOTIONS_CODE",
      "top_fact": false
    },
    {
      "label_code": "MAPI_BRANCH_ORDER_BLOCK",
      "values": [
        {
          "value_code": "BOOLEAN_FALSE",
          "value": "No",
          "boolean_value": false
        }
      ],
      "category_code": "MAPI_BRANCH_ORDER_BLOCK",
      "top_fact": false
    },
    {
      "label_code": "MAPI_EXPORTABLE",
      "values": [
        {
          "value_code": "BOOLEAN_TRUE",
          "value": "Yes",
          "boolean_value": true
        }
      ],
      "category_code": "MAPI_EXPORTABLE",
      "top_fact": false
    }
  ],
  "chemicals_declaration": {
    "release_date": "2016-05-30T11:33:56+0200",
    "supplier_id": "0010011162",
    "supplier_description": "A. Marchon SA",
    "hazard_statements": [
      {
        "code": "H319",
        "label": "Causes serious eye irritation."
      }
    ],
    "precautionary_statements": [
      {
        "code": "P101",
        "label": "If medical advice is needed, have product container or label at hand."
      },
      {
        "code": "P102",
        "label": "Keep out of reach of children."
      },
      {
        "code": "P103",
        "label": "Read label before use."
      },
      {
        "code": "P264",
        "label": "Wash thoroughly after handling."
      },
      {
        "code": "P280",
        "label": "Wear protective gloves / protective clothing / eye protection / face protection."
      },
      {
        "code": "P305_351_338",
        "label": "IF IN EYES: Rinse cautiously with water for several minutes. Remove contact lenses, if present and easy to do. Continue rinsing."
      },
      {
        "code": "P337_313",
        "label": "If eye irritation persists: Get medical advice/attention."
      }
    ],
    "storage_class": {
      "code": "LK13",
      "label": "13 Non-flammable solids in non-flammable package"
    },
    "signal_word": {
      "code": "SW02",
      "label": "Warning"
    },
    "cpid_number": "(FM)",
    "poison_cabinet": false,
    "hazard_pictograms": [
      {
        "code": "GHS07",
        "description": "exclamation mark",
        "original": "https://image.migros.ch/original/09b3c0810d45b7f83a5ad48c5bc38d4d0227615b/GHS07.jpg",
        "stack": "https://image.migros.ch/{stack}/09b3c0810d45b7f83a5ad48c5bc38d4d0227615b/GHS07.jpg"
      }
    ]
  },
  "recipe_ingredient_ids": [
    "10000"
  ],
  "regional_availability": {
    "gmaa": {
      "probability": 0
    },
    "gmbs": {
      "probability": 10
    },
    "gmge": {
      "probability": 0
    },
    "gmlu": {
      "probability": 7
    },
    "gmnf": {
      "probability": 0
    },
    "gmos": {
      "probability": 0
    },
    "gmti": {
      "probability": 3
    },
    "gmvd": {
      "probability": 0
    },
    "gmvs": {
      "probability": 15
    },
    "gmzh": {
      "probability": 0
    }
  },
  "quantity_on_stock": 300,
  "reindex_date": "9999-12-31T00:00:00+0100",
  "updated_at": "2023-08-17T07:43:35+0200",
  "sap_created_at": "2009-06-25T00:00:00+0200",
  "base_unit": "CU",
  "views": [
    "all",
    "browse",
    "browseallretailers"
  ]
}
