{
  "id": "704527600000",
  "language": "en",
  "name": "SILICONE COVER",
  "names": {
    "short_name": "SILICONE COVER"
  },
  "slug": "silicone-cover",
  "slugs": {
    "de": "generation-m-recover",
    "fr": "generation-m-recover",
    "it": "generation-m-recover",
    "en": "silicone-cover"
  },
  "type": "00",
  "boss_number": "150432232005",
  "description": {
    "text": "Wiederverwendbare Silikondeckel, die mit einem Durchmesser von 10 cm prima auf offene Joghurtbecher und Co. passen.",
    "source": "PEX"
  },
  "data_source": "SAP-X12",
  "status": {
    "id": "available",
    "seasonal": false,
    "pim_status": "03",
    "distribution_center": [
      {
        "center_id": "1001",
        "center_name": "Migros Verteilzentrum Neuendorf",
        "status_code": "03",
        "status_description": "active"
      }
    ]
  },
  "tags": [
    "source-pex",
    "near-non-food",
    "migipedia",
    "view-browse-partial",
    "view-browse-all-retailers-partial"
  ],
  "is_variant": false,
  "gtins": [
    "7613434057170"
  ],
  "retailer": {
    "id": "supermarkt",
    "name": "Supermarket"
  },
  "retailer_flags": {
    "bikeworld": {
      "orderable": false,
      "reservable": true,
      "stock_request": true,
      "visible": false,
      "exclude_cross_channel": []
    },
    "doitgarden": {
      "orderable": false,
      "reservable": true,
      "stock_request": true,
      "visible": false,
      "exclude_cross_channel": []
    },
    "interio": {
      "orderable": false,
      "reservable": true,
      "stock_request": true,
      "visible": false,
      "exclude_cross_channel": []
    },
    "melectronics": {
      "orderable": false,
      "reservable": true,
      "stock_request": true,
      "visible": false,
      "exclude_cross_channel": []
    },
    "micasa": {
      "orderable": false,
      "reservable": true,
      "stock_request": true,
      "visible": false,
      "exclude_cross_channel": []
    },
    "migros_ch": {
      "orderable": false,
      "reservable": false,
      "stock_request": false,
      "visible": true,
      "exclude_cross_channel": []
    },
    "sportxx": {
      "orderable": false,
      "reservable": true,
      "stock_request": true,
      "visible": false,
      "exclude_cross_channel": []
    }
  },
  "categories": [
    {
      "code": "BeSS_01042102",
      "name": "Frischhalten & Aufbewahren",
      "slug": "supermarkt/haushalt-reinigung/frischhalten-backen-aufbewahren/frischhalten-aufbewahren",
      "visible": true,
      "parent_code": "BeSS_010421",
      "level": 4
    },
    {
      "code": "BeSS_010421",
      "name": "Frischhalten, Backen & Aufbewahren",
      "slug": "supermarkt/haushalt-reinigung/frischhalten-backen-aufbewahren",
      "visible": true,
      "parent_code": "BeSS_0104",
      "level": 3
    },
    {
      "code": "BeSS_0104",
      "name": "Haushalt & Reinigung",
      "slug": "supermarkt/haushalt-reinigung",
      "visible": true,
      "title": "Reinigung mit der Migros – Reiniger für Haushalt und Garten",
      "parent_code": "BeSS_01",
      "image": {
        "original": "https://image.migros.ch/original/e5da3225980543e0c7ddcc443069f331d94e8439/haushalt-reinigung.png",
        "stack": "https://image.migros.ch/{stack}/e5da3225980543e0c7ddcc443069f331d94e8439/haushalt-reinigung.png"
      },
      "level": 2
    },
    {
      "code": "BeSS_01",
      "name": "Supermarkt",
      "slug": "supermarkt",
      "visible": true,
      "parent_code": "root",
      "level": 1
    }
  ],
  "online_relevant": [
    {
      "code": "MGB",
      "name": "Migros Genossenschafts-Bund"
    },
    {
      "code": "MO",
      "name": "Migros Online"
    }
  ],
  "links": {
    "migros_ch": {
      "url": "https://www.migros.ch/en/product/704527600000?context=instore",
      "name": "In-store assortment",
      "canonical": "https://www.migros.ch/en/product/704527600000?context=instore",
      "type": "info",
      "purchasable": false
    },
    "migros_online": {
      "url": "https://www.migros.ch/en/product/704527600000?context=online",
      "mo_product_id": "7070203",
      "name": "Online-shop assortment",
      "canonical": "https://www.migros.ch/en/product/704527600000?context=instore",
      "type": "shop",
      "purchasable": true,
      "one_catalog_id": 100054706
    },
    "migipedia": {
      "url": "https://migipedia.migros.ch/de/products/704527600000",
      "name": "Migipedia",
      "canonical": "https://www.migros.ch/en/product/704527600000?context=instore",
      "type": "info",
      "purchasable": false
    }
  },
  "m_check2": {
    "carbon_footprint": {
      "image": {
        "original": "https://image.migros.ch/original/6137c42cbff331738ddeafb4f91efb06075417b3.svg",
        "stack": "https://image.migros.ch/{stack}/6137c42cbff331738ddeafb4f91efb06075417b3.svg"
      },
      "ground_and_sea_cargo": {
        "kg_co2": 6.64,
        "kg_co2_range": "4.8 - 9.9 kg CO₂eq / kg",
        "co2_in_car_km": 36,
        "rating": 2,
        "production_in_percent": 96,
        "packaging_in_percent": 3,
        "transport_in_percent": 2
      }
    }
  },
  "warranty_months": 24,
  "receipt_text": "Silikondeckel",
  "package": {
    "content": 1,
    "content_unit_code": "st",
    "content_unit": "Stück",
    "brutto_weight": 0.27,
    "brutto_weight_unit_code": "kg",
    "brutto_volume": 0.072,
    "brutto_volume_unit_code": "cdm",
    "height": 0.5,
    "length": 12,
    "width": 12,
    "unit_dimension": "cm",
    "price_comparison_content": 1,
    "size": "1 Stk."
  },
  "package_information": {
    "cu": {
      "gtins": [
        "7613434057170"
      ],
      "brutto_weight": 0.27,
      "brutto_weight_unit_code": "kg",
      "brutto_volume": 0.072,
      "brutto_volume_unit_code": "cdm",
      "height": 0.5,
      "length": 12,
      "width": 12,
      "dimension_unit_code": "cm",
      "number_of_base_units": 1
    },
    "tuv": {
      "brutto_weight": 0.63,
      "brutto_weight_unit_code": "kg",
      "brutto_volume": 2.535,
      "brutto_volume_unit_code": "cdm",
      "height": 13,
      "length": 15,
      "width": 13,
      "dimension_unit_code": "cm",
      "number_of_base_units": 20
    },
    "tue": {
      "brutto_weight": 0.62,
      "brutto_weight_unit_code": "kg",
      "brutto_volume": 3.15,
      "brutto_volume_unit_code": "cdm",
      "height": 14,
      "length": 15,
      "width": 15,
      "dimension_unit_code": "cm",
      "number_of_base_units": 20
    },
    "lu": {
      "number_of_base_units": 1
    }
  },
  "vat": {
    "id": 1,
    "percentage": 7.7
  },
  "price": {
    "valid_from": "2021-04-07T00:00:00+0200",
    "valid_to": "9999-12-31T23:59:59+0100",
    "currency": "CHF",
    "source": "PriceRepository",
    "item": {
      "price": 1.95,
      "quantity": 1,
      "unit": "CU",
      "varying_quantity": false,
      "display_quantity": "1 Stk."
    },
    "base": {
      "price": 1.95,
      "quantity": 1,
      "unit": "st"
    }
  },
  "features": [
    {
      "label_code": "miso_farbe",
      "label": "Color",
      "values": [
        {
          "value_code": "MISO_farbe_gruen",
          "value": "grün"
        }
      ],
      "category_code": "MISO_CLA_FolienBeutel_Verbrauch_Haushalt_Alle",
      "top_fact": false,
      "facet_flag": false,
      "facet_pictogram_flag": false
    },
    {
      "label_code": "miso_durchmesser",
      "label": "Diameter",
      "values": [
        {
          "value_code": "NUMERIC_10",
          "value": "10 cm",
          "numeric_value": 10
        }
      ],
      "category_code": "MISO_CLA_Kueche_Haushalt_Alle",
      "top_fact": false,
      "unit_code": "cm",
      "unit": "Zentimeter",
      "unit_symbol": "cm",
      "facet_flag": false,
      "facet_pictogram_flag": false
    },
    {
      "label_code": "miso_material",
      "label": "Material",
      "values": [
        {
          "value_code": "MISO_material_silikion",
          "value": "Silikon"
        }
      ],
      "category_code": "MISO_CLA_Kueche_Haushalt_Alle",
      "top_fact": false,
      "facet_flag": false,
      "facet_pictogram_flag": false
    },
    {
      "label_code": "miso_farbe",
      "label": "Color",
      "values": [
        {
          "value_code": "MISO_farbe_gruen",
          "value": "grün"
        }
      ],
      "category_code": "MISO_CLA_Kueche_Haushalt_Alle",
      "top_fact": false,
      "facet_flag": false,
      "facet_pictogram_flag": false
    },
    {
      "label_code": "miso_fuer_lebensmittel_geeignet",
      "label": "suitable for food products",
      "values": [
        {
          "value_code": "BOOLEAN_TRUE",
          "value": "Yes",
          "boolean_value": true
        }
      ],
      "category_code": "MISO_CLA_Kueche_Haushalt_Alle",
      "top_fact": false,
      "facet_flag": false,
      "facet_pictogram_flag": false
    },
    {
      "label_code": "miso_spuelmaschinentauglich",
      "label": "Dishwasher-safe",
      "values": [
        {
          "value_code": "BOOLEAN_TRUE",
          "value": "Yes",
          "boolean_value": true
        }
      ],
      "category_code": "MISO_CLA_Kueche_Haushalt_Alle",
      "top_fact": false,
      "facet_flag": false,
      "facet_pictogram_flag": false
    }
  ],
  "image": {
    "original": "https://image.migros.ch/original/b73f4b1cc36fb0ae74acdf4aa563e690de0492c7/silicone-cover.jpg",
    "stack": "https://image.migros.ch/{stack}/b73f4b1cc36fb0ae74acdf4aa563e690de0492c7/silicone-cover.jpg"
  },
  "image_transparent": {
    "original": "https://image.migros.ch/original/7535868ef952daf6602f3da8977f2ebe7addb16b/silicone-cover.png",
    "stack": "https://image.migros.ch/{stack}/7535868ef952daf6602f3da8977f2ebe7addb16b/silicone-cover.png"
  },
  "additional_images": [
    {
      "original": "https://image.migros.ch/original/cd7f5062a069808f101cf737a470d59620efc5e4.jpg",
      "stack": "https://image.migros.ch/{stack}/cd7f5062a069808f101cf737a470d59620efc5e4.jpg"
    },
    {
      "original": "https://image.migros.ch/original/74133b8212869885439f19c805c937ab30b45711.jpg",
      "stack": "https://image.migros.ch/{stack}/74133b8212869885439f19c805c937ab30b45711.jpg"
    }
  ],
  "internal_features": [
    {
      "label_code": "MAPI_DEFAULT_LOGISTIC_TYPE",
      "values": [
        {
          "value_code": "55",
          "value": "Versandart Paket"
        }
      ],
      "category_code": "MAPI_DEFAULT_LOGISTIC_TYPE",
      "top_fact": false
    },
    {
      "label_code": "MAPI_LOGISTIC_CLASS",
      "values": [
        {
          "value_code": "1",
          "value": "Lager"
        }
      ],
      "category_code": "MAPI_LOGISTIC_CLASS",
      "top_fact": false
    },
    {
      "label_code": "MAPI_GENERAL_POSITION_GROUP",
      "values": [
        {
          "value_code": "NORM",
          "value": "Standard item"
        }
      ],
      "category_code": "MAPI_GENERAL_POSITION_GROUP",
      "top_fact": false
    },
    {
      "label_code": "MAPI_ARTICLE_VARIETY",
      "values": [
        {
          "value": "HART"
        }
      ],
      "category_code": "MAPI_ARTICLE_VARIETY",
      "top_fact": false
    },
    {
      "label_code": "MAPI_QUALITY_CHECK",
      "values": [
        {
          "value_code": "02",
          "value": "FRI (Final Random Inspection)"
        }
      ],
      "category_code": "MAPI_QUALITY_CHECK",
      "top_fact": false
    },
    {
      "label_code": "MAPI_KUBE_TUKA",
      "values": [
        {
          "value_code": "BLANK",
          "value": "KUBE und TUKA nicht zugelassen"
        }
      ],
      "category_code": "MAPI_KUBE_TUKA",
      "top_fact": false
    },
    {
      "label_code": "MAPI_PRODUCT_KIND",
      "values": [
        {
          "value_code": "HART",
          "value": "Hartwaren Handelsware"
        }
      ],
      "category_code": "MAPI_PRODUCT_KIND",
      "top_fact": false
    },
    {
      "label_code": "MAPI_ASSORTMENT_LIST_KIND",
      "values": [
        {
          "value_code": "H",
          "value": "Hartwaren"
        }
      ],
      "category_code": "MAPI_ASSORTMENT_LIST_KIND",
      "top_fact": false
    },
    {
      "label_code": "MAPI_PRODUCT_GROUP",
      "values": [
        {
          "value_code": "60517",
          "value": "FRISCHHALTEN"
        }
      ],
      "category_code": "MAPI_PRODUCT_GROUP",
      "top_fact": false
    },
    {
      "label_code": "MAPI_CUMULUS_POINTS_CODE",
      "values": [
        {
          "value_code": "NUMERIC_2",
          "value": "2",
          "numeric_value": 2
        }
      ],
      "category_code": "MAPI_CUMULUS_POINTS_CODE",
      "top_fact": false
    },
    {
      "label_code": "MAPI_PROMOTIONS_CODE",
      "values": [
        {
          "value_code": "NUMERIC_1",
          "value": "1",
          "numeric_value": 1
        }
      ],
      "category_code": "MAPI_PROMOTIONS_CODE",
      "top_fact": false
    },
    {
      "label_code": "MAPI_BRANCH_ORDER_BLOCK",
      "values": [
        {
          "value_code": "BOOLEAN_FALSE",
          "value": "No",
          "boolean_value": false
        }
      ],
      "category_code": "MAPI_BRANCH_ORDER_BLOCK",
      "top_fact": false
    },
    {
      "label_code": "MAPI_EXPORTABLE",
      "values": [
        {
          "value_code": "BOOLEAN_FALSE",
          "value": "No",
          "boolean_value": false
        }
      ],
      "category_code": "MAPI_EXPORTABLE",
      "top_fact": false
    }
  ],
  "recipe_ingredient_ids": [
    "10000"
  ],
  "regional_availability": {
    "gmaa": {
      "probability": 94
    },
    "gmbs": {
      "probability": 95
    },
    "gmge": {
      "probability": 74
    },
    "gmlu": {
      "probability": 92
    },
    "gmnf": {
      "probability": 94
    },
    "gmos": {
      "probability": 87
    },
    "gmti": {
      "probability": 97
    },
    "gmvd": {
      "probability": 95
    },
    "gmvs": {
      "probability": 89
    },
    "gmzh": {
      "probability": 87
    }
  },
  "colors": [
    {
      "label": "grün",
      "hex": "#008000",
      "group": "Grün",
      "group_hex": "#008000"
    },
    {
      "label": "grün",
      "hex": "#008000",
      "group": "Grün",
      "group_hex": "#008000"
    }
  ],
  "ratings": {
    "count_all": 28,
    "average_all": 4.071428571429
  },
  "quantity_on_stock": 160000,
  "reindex_date": "9999-12-31T00:00:00+0100",
  "updated_at": "2023-08-17T12:05:04+0200",
  "sap_created_at": "2021-02-26T00:00:00+0100",
  "base_unit": "CU",
  "origins": {
    "producing_country": "China"
  },
  "views": [
    "all",
    "browse",
    "browseallretailers"
  ]
}
