{
  "id": "724224600000",
  "language": "en",
  "name": "ACRYL FARBEN SET, 24STK, BUNT",
  "names": {
    "short_name": "ACRYL FARBEN SET, 24STK, BUNT"
  },
  "slug": "acryl-farben-set-24stk-bunt",
  "slugs": {
    "de": "acrylfarben-auf-wasserbasis",
    "fr": "peintures-acryliques-a-base-deau",
    "it": "vernici-acrliche-base-dacqua",
    "en": "acryl-farben-set-24stk-bunt"
  },
  "type": "00",
  "boss_number": "150310331510",
  "data_source": "SAP-X12",
  "status": {
    "id": "available",
    "seasonal": false,
    "pim_status": "03",
    "distribution_center": [
      {
        "center_id": "1001",
        "center_name": "Migros Verteilzentrum Neuendorf",
        "status_code": "03",
        "status_description": "active"
      }
    ]
  },
  "tags": [
    "source-pex",
    "near-non-food",
    "migipedia",
    "view-browse-partial",
    "view-browse-all-retailers-partial"
  ],
  "is_variant": false,
  "gtins": [
    "7611983218769"
  ],
  "retailer": {
    "id": "supermarkt",
    "name": "Supermarket"
  },
  "retailer_flags": {
    "bikeworld": {
      "orderable": false,
      "reservable": true,
      "stock_request": true,
      "visible": false,
      "exclude_cross_channel": []
    },
    "doitgarden": {
      "orderable": false,
      "reservable": true,
      "stock_request": true,
      "visible": false,
      "exclude_cross_channel": []
    },
    "interio": {
      "orderable": false,
      "reservable": true,
      "stock_request": true,
      "visible": false,
      "exclude_cross_channel": []
    },
    "melectronics": {
      "orderable": false,
      "reservable": true,
      "stock_request": true,
      "visible": false,
      "exclude_cross_channel": []
    },
    "micasa": {
      "orderable": false,
      "reservable": true,
      "stock_request": true,
      "visible": false,
      "exclude_cross_channel": []
    },
    "migros_ch": {
      "orderable": false,
      "reservable": false,
      "stock_request": false,
      "visible": true,
      "exclude_cross_channel": []
    },
    "sportxx": {
      "orderable": false,
      "reservable": true,
      "stock_request": true,
      "visible": false,
      "exclude_cross_channel": []
    }
  },
  "brand": {
    "id": "I54",
    "name": "I AM CREATIVE",
    "slug": "i-am-creative",
    "image": {
      "original": "https://image.migros.ch/original/033daa5650065308160672585624423b2603dbad/i-am-creative.jpg",
      "stack": "https://image.migros.ch/{stack}/033daa5650065308160672585624423b2603dbad/i-am-creative.jpg"
    }
  },
  "categories": [
    {
      "code": "BeSS_010505",
      "name": "Malen & Zeichnen",
      "slug": "supermarkt/papeterie-bueromaterial/malen-zeichnen",
      "visible": true,
      "title": "Malen und Zeichnen – mit Material von Ihrer Migros",
      "parent_code": "BeSS_0105",
      "level": 3
    },
    {
      "code": "BeSS_0105",
      "name": "Papeterie & Büromaterial",
      "slug": "supermarkt/papeterie-bueromaterial",
      "visible": true,
      "title": "Papeterie und Büromaterialien sind immer in Ihrer Migros zu finden",
      "parent_code": "BeSS_01",
      "image": {
        "original": "https://image.migros.ch/original/6b764b62482953963a5ab3263b9bd3a69cbf436a/papeterie-bueromaterial.jpg",
        "stack": "https://image.migros.ch/{stack}/6b764b62482953963a5ab3263b9bd3a69cbf436a/papeterie-bueromaterial.jpg"
      },
      "level": 2
    },
    {
      "code": "BeSS_01",
      "name": "Supermarkt",
      "slug": "supermarkt",
      "visible": true,
      "parent_code": "root",
      "level": 1
    }
  ],
  "links": {
    "migros_ch": {
      "url": "https://www.migros.ch/en/product/724224600000?context=instore",
      "name": "In-store assortment",
      "canonical": "https://www.migros.ch/en/product/724224600000?context=instore",
      "type": "info",
      "purchasable": false
    },
    "migipedia": {
      "url": "https://migipedia.migros.ch/de/products/724224600000",
      "name": "Migipedia",
      "canonical": "https://www.migros.ch/en/product/724224600000?context=instore",
      "type": "info",
      "purchasable": false
    }
  },
  "m_check2": {},
  "warranty_months": 24,
  "receipt_text": "Acryl Farben Set",
  "package": {
    "net_weight": 0.49,
    "net_weight_unit_code": "kg",
    "net_weight_unit": "Kilogramm",
    "brutto_weight": 0.5,
    "brutto_weight_unit_code": "kg",
    "brutto_volume": 260.544,
    "brutto_volume_unit_code": "ccm",
    "height": 28.5,
    "length": 14,
    "width": 22.5,
    "unit_dimension": "cm",
    "price_comparison_content": 1,
    "size": "24 Stk."
  },
  "package_information": {
    "cu": {
      "gtins": [
        "7611983218769"
      ],
      "brutto_weight": 0.5,
      "brutto_weight_unit_code": "kg",
      "brutto_volume": 260.544,
      "brutto_volume_unit_code": "ccm",
      "height": 28.5,
      "length": 14,
      "width": 22.5,
      "dimension_unit_code": "cm",
      "number_of_base_units": 1
    },
    "tuv": {
      "number_of_base_units": 6
    },
    "tue": {
      "brutto_weight": 3,
      "brutto_weight_unit_code": "kg",
      "brutto_volume": 42.78,
      "brutto_volume_unit_code": "cdm",
      "height": 30,
      "length": 31,
      "width": 46,
      "dimension_unit_code": "cm",
      "number_of_base_units": 6
    },
    "lu": {
      "number_of_base_units": 288
    }
  },
  "vat": {
    "id": 1,
    "percentage": 7.7
  },
  "price": {
    "valid_from": "2022-04-29T00:00:00+0200",
    "valid_to": "9999-12-31T23:59:59+0100",
    "currency": "CHF",
    "source": "PriceRepository",
    "item": {
      "price": 16.95,
      "quantity": 1,
      "unit": "CU",
      "varying_quantity": false,
      "display_quantity": "24 Stk."
    }
  },
  "features": [
    {
      "label_code": "miso_anwendungsbereich",
      "label": "Area of application",
      "values": [
        {
          "value": "auf Leinwand, Papier, Holz, Karton usw."
        }
      ],
      "category_code": "MISO_CLA_MalenZeichnen_Papeterie_Haushalt_Alle",
      "top_fact": false,
      "facet_flag": false,
      "facet_pictogram_flag": false
    },
    {
      "label_code": "miso_inhalt",
      "label": "Content",
      "values": [
        {
          "value": "24 x 12 ml"
        }
      ],
      "category_code": "MISO_CLA_MalenZeichnen_Papeterie_Haushalt_Alle",
      "top_fact": false,
      "facet_flag": false,
      "facet_pictogram_flag": false
    },
    {
      "label_code": "miso_farbe",
      "label": "Color",
      "values": [
        {
          "value_code": "MISO_farbe_assortiert",
          "value": "assortiert"
        }
      ],
      "category_code": "MISO_CLA_MalenZeichnen_Papeterie_Haushalt_Alle",
      "top_fact": false,
      "facet_flag": false,
      "facet_pictogram_flag": false
    }
  ],
  "image": {
    "original": "https://image.migros.ch/original/4fcfa5619593ad158745168f98d147b9188474bf/acryl-farben-set-24stk-bunt.jpg",
    "stack": "https://image.migros.ch/{stack}/4fcfa5619593ad158745168f98d147b9188474bf/acryl-farben-set-24stk-bunt.jpg"
  },
  "image_transparent": {
    "original": "https://image.migros.ch/original/18a45a2fcd8bac93009fe9dfc1ea085e0e66cb15/acryl-farben-set-24stk-bunt.png",
    "stack": "https://image.migros.ch/{stack}/18a45a2fcd8bac93009fe9dfc1ea085e0e66cb15/acryl-farben-set-24stk-bunt.png"
  },
  "internal_features": [
    {
      "label_code": "MAPI_DEFAULT_LOGISTIC_TYPE",
      "values": [
        {
          "value_code": "55",
          "value": "Versandart Paket"
        }
      ],
      "category_code": "MAPI_DEFAULT_LOGISTIC_TYPE",
      "top_fact": false
    },
    {
      "label_code": "MAPI_LOGISTIC_CLASS",
      "values": [
        {
          "value_code": "7",
          "value": "VMI"
        }
      ],
      "category_code": "MAPI_LOGISTIC_CLASS",
      "top_fact": false
    },
    {
      "label_code": "MAPI_GENERAL_POSITION_GROUP",
      "values": [
        {
          "value_code": "NORM",
          "value": "Standard item"
        }
      ],
      "category_code": "MAPI_GENERAL_POSITION_GROUP",
      "top_fact": false
    },
    {
      "label_code": "MAPI_ARTICLE_VARIETY",
      "values": [
        {
          "value": "HART"
        }
      ],
      "category_code": "MAPI_ARTICLE_VARIETY",
      "top_fact": false
    },
    {
      "label_code": "MAPI_PRESENTATION",
      "values": [
        {
          "value_code": "H",
          "value": "hängend"
        }
      ],
      "category_code": "MAPI_PRESENTATION",
      "top_fact": false
    },
    {
      "label_code": "MAPI_RISK_CLASS",
      "values": [
        {
          "value_code": "2",
          "value": "2 (medium)"
        }
      ],
      "category_code": "MAPI_RISK_CLASS",
      "top_fact": false
    },
    {
      "label_code": "MAPI_KUBE_TUKA",
      "values": [
        {
          "value_code": "BLANK",
          "value": "KUBE und TUKA nicht zugelassen"
        }
      ],
      "category_code": "MAPI_KUBE_TUKA",
      "top_fact": false
    },
    {
      "label_code": "MAPI_PRODUCT_KIND",
      "values": [
        {
          "value_code": "HART",
          "value": "Hartwaren Handelsware"
        }
      ],
      "category_code": "MAPI_PRODUCT_KIND",
      "top_fact": false
    },
    {
      "label_code": "MAPI_ASSORTMENT_LIST_KIND",
      "values": [
        {
          "value_code": "H",
          "value": "Hartwaren"
        }
      ],
      "category_code": "MAPI_ASSORTMENT_LIST_KIND",
      "top_fact": false
    },
    {
      "label_code": "MAPI_PRODUCT_GROUP",
      "values": [
        {
          "value_code": "61381",
          "value": "MALEN"
        }
      ],
      "category_code": "MAPI_PRODUCT_GROUP",
      "top_fact": false
    },
    {
      "label_code": "MAPI_CUMULUS_POINTS_CODE",
      "values": [
        {
          "value_code": "NUMERIC_2",
          "value": "2",
          "numeric_value": 2
        }
      ],
      "category_code": "MAPI_CUMULUS_POINTS_CODE",
      "top_fact": false
    },
    {
      "label_code": "MAPI_PROMOTIONS_CODE",
      "values": [
        {
          "value_code": "NUMERIC_1",
          "value": "1",
          "numeric_value": 1
        }
      ],
      "category_code": "MAPI_PROMOTIONS_CODE",
      "top_fact": false
    },
    {
      "label_code": "MAPI_BRANCH_ORDER_BLOCK",
      "values": [
        {
          "value_code": "BOOLEAN_FALSE",
          "value": "No",
          "boolean_value": false
        }
      ],
      "category_code": "MAPI_BRANCH_ORDER_BLOCK",
      "top_fact": false
    },
    {
      "label_code": "MAPI_EXPORTABLE",
      "values": [
        {
          "value_code": "BOOLEAN_FALSE",
          "value": "No",
          "boolean_value": false
        }
      ],
      "category_code": "MAPI_EXPORTABLE",
      "top_fact": false
    }
  ],
  "regional_availability": {
    "gmaa": {
      "probability": 18
    },
    "gmbs": {
      "probability": 12
    },
    "gmge": {
      "probability": 13
    },
    "gmlu": {
      "probability": 15
    },
    "gmnf": {
      "probability": 0
    },
    "gmos": {
      "probability": 15
    },
    "gmti": {
      "probability": 10
    },
    "gmvd": {
      "probability": 14
    },
    "gmvs": {
      "probability": 19
    },
    "gmzh": {
      "probability": 16
    }
  },
  "quantity_on_stock": 90,
  "reindex_date": "9999-12-31T00:00:00+0100",
  "updated_at": "2023-08-10T08:00:57+0200",
  "sap_created_at": "2022-04-29T00:00:00+0200",
  "online_shop_relevant": true,
  "base_unit": "CU",
  "views": [
    "all",
    "browse",
    "browseallretailers"
  ]
}
